asha/.asha
asha/.gitignore
asha/__init__.py
asha/config.json
asha/hacks.py
asha/lib.py
asha/utils.py
asha/pages/about.md
asha/pages/blog.md
asha/pages/index.md
asha/posts/2020/first_post.md
asha/posts/2020/second_post.md
asha/themes/default/config.json
asha/themes/default/footer.jinja
asha/themes/default/header.jinja
asha/themes/default/main.jinja
asha/themes/default/page.jinja
asha/themes/default/post.jinja
asha/themes/default/posts.jinja
asha/themes/default/pages/about.json
asha/themes/default/pages/index.json
asha/themes/default/posts/2020/first_post.json
asha/themes/default/posts/2020/second_post.json
asha/themes/default/static/css/main.css
asha/themes/default/static/images/logo.jpeg
asha-0.0.4.dist-info/LICENSE
asha-0.0.4.dist-info/METADATA
asha-0.0.4.dist-info/WHEEL
asha-0.0.4.dist-info/entry_points.txt
asha-0.0.4.dist-info/top_level.txt
asha-0.0.4.dist-info/RECORD
